{
  "entity": {
    "name": "PredictionTable",
    "pk": "id",
    "description": "SE practice prediction table",
    "attributes": [
      {
        "name": "name",
        "type": "string",
        "description": "Prediction table name"
      }
    ]
  },
  "relationships": [
    {
      "name": "predictionTableEntry",
      "type": "oneToMany",
      "to": "PredictionTableEntry",
      "description": "Entries for this table"
    },
    {
      "name": "letterElement",
      "type": "oneToMany",
      "to": "LetterElement",
      "description": "Letter elements that use this table"
    }
  ]
}
